gen_mqtt_service/__init__.py
gen_mqtt_service/py.typed
gen_mqtt_service/conf/gen_mqtt_service.cfg
gen_mqtt_service/conf/gen_mqtt_service.logo
gen_mqtt_service/conf/gen_mqtt_service_util.cfg
gen_mqtt_service/conf/project.yaml
gen_mqtt_service/conf/template/mosquitto/publisher.template
gen_mqtt_service/conf/template/mosquitto/subscriber.template
gen_mqtt_service/conf/template/node/publisher.template
gen_mqtt_service/conf/template/node/subscriber.template
gen_mqtt_service/conf/template/node_ws/client.template
gen_mqtt_service/conf/template/node_ws/server.template
gen_mqtt_service/conf/template/paho/publisher.template
gen_mqtt_service/conf/template/paho/subscriber.template
gen_mqtt_service/log/gen_mqtt_service.log
gen_mqtt_service/pro/__init__.py
gen_mqtt_service/pro/read_template.py
gen_mqtt_service/pro/write_template.py
usr/local/bin/gen_mqtt_service_run.py
gen_mqtt_service-1.1.3.dist-info/LICENSE
gen_mqtt_service-1.1.3.dist-info/METADATA
gen_mqtt_service-1.1.3.dist-info/WHEEL
gen_mqtt_service-1.1.3.dist-info/top_level.txt
gen_mqtt_service-1.1.3.dist-info/RECORD
